nicobot/__init__.py
nicobot/askbot.py
nicobot/bot.py
nicobot/chatter.py
nicobot/console.py
nicobot/helpers.py
nicobot/jabber.py
nicobot/signalcli.py
nicobot/stealth.py
nicobot/transbot.py
nicobot/version.py
nicobot-0.1.10.dist-info/LICENSE
nicobot-0.1.10.dist-info/METADATA
nicobot-0.1.10.dist-info/WHEEL
nicobot-0.1.10.dist-info/entry_points.txt
nicobot-0.1.10.dist-info/top_level.txt
nicobot-0.1.10.dist-info/RECORD
