Metadata-Version: 2.1
Name: nicobot
Version: 0.1.10
Summary: A collection of 🤟 cool 🤟 chat bots
Home-page: https://github.com/nicolabs/nicobot
Author: nicobo
Author-email: nicobo@users.noreply.github.com
License: UNKNOWN
Platform: UNKNOWN
Classifier: Programming Language :: Python :: 3
Classifier: License :: OSI Approved :: MIT License
Classifier: Operating System :: OS Independent
Classifier: Development Status :: 3 - Alpha
Classifier: Topic :: Communications :: Chat
Classifier: Topic :: Internet :: XMPP
Classifier: Topic :: Scientific/Engineering :: Interface Engine/Protocol Translator
Classifier: Topic :: Software Development :: Internationalization
Requires-Python: >=3.5
Requires-Dist: python-i18n
Requires-Dist: requests
Requires-Dist: emoji-country-flag
Requires-Dist: pyyaml
Requires-Dist: slixmpp-omemo
